fbauth/__init__.py
fbauth/commands.py
fbauth/extension.py
fbauth/forms.py
fbauth/graphql/__init__.py
fbauth/graphql/role.py
fbauth/graphql/user.py
fbauth/manager/__init__.py
fbauth/manager/role.py
fbauth/manager/user.py
fbauth/middleware.py
fbauth/permissions.py
fbauth/router.py
fbauth/security/__init__.py
fbauth/security/config.py
fbauth/security/hashing.py
fbauth/security/tokens.py
fbauth/testing/client.graphql
fbauth/types.py
fbauth-0.0.10.dist-info/WHEEL
fbauth-0.0.10.dist-info/METADATA
fbauth-0.0.10.dist-info/licenses/LICENSE
fbauth-0.0.10.dist-info/RECORD
